classes/__init__.py
classes/bloc.py
classes/client.py
classes/code.py
classes/commentaire.py
classes/parser.py
classes/requete.py
classes/script.py
classes/table.py
classes/variable.py
elucidata/__init__.py
elucidata/const_regex.py
elucidata/dataviz.py
elucidata/parser.py
elucidata/utils.py
elucidata/classes/__init__.py
elucidata/classes/bloc.py
elucidata/classes/client.py
elucidata/classes/code.py
elucidata/classes/commentaire.py
elucidata/classes/parser.py
elucidata/classes/requete.py
elucidata/classes/script.py
elucidata/classes/table.py
elucidata/classes/variable.py
elucidata-0.0.8.dist-info/LICENSE
elucidata-0.0.8.dist-info/METADATA
elucidata-0.0.8.dist-info/WHEEL
elucidata-0.0.8.dist-info/top_level.txt
elucidata-0.0.8.dist-info/RECORD
