Metadata-Version: 2.1
Name: elucidata
Version: 0.0.8
Summary: A python module to parse source code for retro-documentation
Home-page: https://bitbucket.org/bi_labbigdata/parser/src/master/
Author: Nicolas Bouillette, Guillaume Hurvois, Julien Mendes, Adam Wang
Author-email: nbouillette@bi-consulting.com, ghurvois@bi-consulting.com, jmendes@bi-consulting.com, awang@bi-consulting.com
License: UNKNOWN
Platform: UNKNOWN
Requires-Python: >=3.7
